eeSDM/__init__.py
eeSDM/__version__.py
eeSDM/eeSDM.py
eeSDM-0.1.3.dist-info/METADATA
eeSDM-0.1.3.dist-info/WHEEL
eeSDM-0.1.3.dist-info/top_level.txt
eeSDM-0.1.3.dist-info/RECORD
