Metadata-Version: 2.1
Name: eeSDM
Version: 0.1.3
Summary: Google Earth Engine-based Species Distribution Modeling
Home-page: https://github.com/osgeokr/eeSDM
Author: Byeong-Hyeok Yu
Author-email: bhyu@knps.or.kr
Classifier: Development Status :: 4 - Beta
Classifier: License :: OSI Approved :: GNU General Public License v3 (GPLv3)
Classifier: Programming Language :: Python :: 3.6
Classifier: Programming Language :: Python :: 3.7
Classifier: Programming Language :: Python :: 3.8
Classifier: Programming Language :: Python :: 3.9
Classifier: Programming Language :: Python :: 3.10
Requires-Python: >=3.6
Requires-Dist: earthengine-api
Requires-Dist: geemap
Requires-Dist: pandas
Requires-Dist: geopandas
Requires-Dist: matplotlib
Requires-Dist: numpy
Requires-Dist: statsmodels
